permetrics/__init__.py
permetrics/classification.py
permetrics/clustering.py
permetrics/evaluator.py
permetrics/regression.py
permetrics/utils/__init__.py
permetrics/utils/classifier_util.py
permetrics/utils/cluster_util.py
permetrics/utils/constant.py
permetrics/utils/data_util.py
permetrics/utils/encoder.py
permetrics/utils/regressor_util.py
permetrics-2.0.0.dist-info/LICENSE
permetrics-2.0.0.dist-info/METADATA
permetrics-2.0.0.dist-info/WHEEL
permetrics-2.0.0.dist-info/top_level.txt
permetrics-2.0.0.dist-info/RECORD
